hamsci_psws/__init__.py
hamsci_psws/calcSun.py
hamsci_psws/gen_lib.py
hamsci_psws/geopack.py
hamsci_psws/goes.py
hamsci_psws/grape1.py
hamsci_psws/locator.py
hamsci_psws/solar.py
hamsci_psws-0.1.3.dist-info/LICENSE
hamsci_psws-0.1.3.dist-info/METADATA
hamsci_psws-0.1.3.dist-info/WHEEL
hamsci_psws-0.1.3.dist-info/top_level.txt
hamsci_psws-0.1.3.dist-info/RECORD
