Metadata-Version: 2.1
Name: hamsci-psws
Version: 0.1.3
Summary: HamSCI Grape v1 Personal Space Weather Station Plotting Tools
Author: Kristina V. Collins
Author-email: "Nathaniel A. Frissell" <nathaniel.frissell@scranton.edu>
License: GNU GENERAL PUBLIC LICENSE
Project-URL: Homepage, https://github.com/HamSCI/hamsci_psws
Project-URL: Bug Tracker, https://github.com/HamSCI/hamsci_psws/issues
Project-URL: HamSCI Website, https://hamsci.org
Classifier: Programming Language :: Python :: 3
Classifier: License :: OSI Approved :: GNU General Public License v3 (GPLv3)
Classifier: Operating System :: OS Independent
Requires-Python: >=3.6
License-File: LICENSE
Requires-Dist: beautifulsoup4
Requires-Dist: matplotlib
Requires-Dist: netCDF4
Requires-Dist: numpy
Requires-Dist: pandas
Requires-Dist: plotly
Requires-Dist: python-dateutil
Requires-Dist: pytz
Requires-Dist: requests
Requires-Dist: scipy
Requires-Dist: suntime
Requires-Dist: tqdm
Requires-Dist: xarray
